billingo/__init__.py
billingo/api_client.py
billingo/configuration.py
billingo/rest.py
billingo/api/__init__.py
billingo/api/bank_account_api.py
billingo/api/currency_api.py
billingo/api/document_api.py
billingo/api/document_block_api.py
billingo/api/document_export_api.py
billingo/api/organization_api.py
billingo/api/partner_api.py
billingo/api/product_api.py
billingo/api/spending_api.py
billingo/api/util_api.py
billingo/models/__init__.py
billingo/models/address.py
billingo/models/bank_account.py
billingo/models/bank_account_list.py
billingo/models/category.py
billingo/models/check_tax_number_message.py
billingo/models/client_error.py
billingo/models/client_error_response.py
billingo/models/conversation_rate.py
billingo/models/correction_type.py
billingo/models/country.py
billingo/models/create_document_export.py
billingo/models/currency.py
billingo/models/date_type.py
billingo/models/discount.py
billingo/models/discount_type.py
billingo/models/document.py
billingo/models/document_ancestor.py
billingo/models/document_bank_account.py
billingo/models/document_block.py
billingo/models/document_block_list.py
billingo/models/document_block_type.py
billingo/models/document_cancellation.py
billingo/models/document_export_filter_extra.py
billingo/models/document_export_id.py
billingo/models/document_export_other_options.py
billingo/models/document_export_query_type.py
billingo/models/document_export_sort_by.py
billingo/models/document_export_status.py
billingo/models/document_export_status_state.py
billingo/models/document_export_type.py
billingo/models/document_form.py
billingo/models/document_format.py
billingo/models/document_insert.py
billingo/models/document_insert_type.py
billingo/models/document_item.py
billingo/models/document_item_data.py
billingo/models/document_language.py
billingo/models/document_list.py
billingo/models/document_notification_status.py
billingo/models/document_organization.py
billingo/models/document_partner.py
billingo-0.0.1.dist-info/METADATA
billingo-0.0.1.dist-info/WHEEL
billingo-0.0.1.dist-info/top_level.txt
billingo-0.0.1.dist-info/RECORD
