Metadata-Version: 2.1
Name: billingo
Version: 0.0.1
Summary: Billingo API v3
Home-page: https://www.axonltd.hu/
Author-email: github@axonltd.hu
Keywords: Swagger,Billingo API v3
Requires-Dist: urllib3 >=1.15
Requires-Dist: six >=1.10
Requires-Dist: certifi
Requires-Dist: python-dateutil
